MANIFEST.in
__info__.py
setup.py
./appomatic_django_cms.egg-info/SOURCES.txt
./appomatic_django_cms.egg-info/dependency_links.txt
./appomatic_django_cms.egg-info/requires.txt
./appomatic_django_cms.egg-info/top_level.txt
./appomatic_django_cms/cms/templates/example.html
appomatic_django_cms/__app__.py
appomatic_django_cms/__init__.py
appomatic_django_cms.egg-info/PKG-INFO
appomatic_django_cms.egg-info/SOURCES.txt
appomatic_django_cms.egg-info/dependency_links.txt
appomatic_django_cms.egg-info/requires.txt
appomatic_django_cms.egg-info/top_level.txt
appomatic_django_cms/articleurls/__app__.py
appomatic_django_cms/articleurls/__init__.py
appomatic_django_cms/articleurls/__urls__.py
appomatic_django_cms/cms/__app__.py
appomatic_django_cms/cms/__init__.py
appomatic_django_cms/cms/__settings__.py
appomatic_django_cms/cms/templates/__init__.py