Metadata-Version: 1.0
Name: appomatic-django-cms
Version: 0.0.32
Summary: Get the pony powered CMS With Frontend-Editing
Home-page: https://www.django-cms.org
Author: RedHog (Egil Moeller)
Author-email: egil.moller@freecode.no
License: GPL
Keywords: appomatic django-cms
Platform: UNKNOWN
